collective.contentgroups-1.0.0a1-py2.7-nspkg.pth
collective/contentgroups/__init__.py
collective/contentgroups/adapters.py
collective/contentgroups/behavior.py
collective/contentgroups/config.py
collective/contentgroups/configure.zcml
collective/contentgroups/interfaces.py
collective/contentgroups/plugins.py
collective/contentgroups/setuphandlers.py
collective/contentgroups/subscribers.py
collective/contentgroups/testing.py
collective/contentgroups/update_locales.sh
collective/contentgroups/utils.py
collective/contentgroups/locales/collective.contentgroups.pot
collective/contentgroups/locales/nl/LC_MESSAGES/collective.contentgroups.mo
collective/contentgroups/locales/nl/LC_MESSAGES/collective.contentgroups.po
collective/contentgroups/profiles/default/metadata.xml
collective/contentgroups/profiles/uninstall/metadata.xml
collective/contentgroups/tests/__init__.py
collective/contentgroups/tests/test_adapters.py
collective/contentgroups/tests/test_functional.py
collective/contentgroups/tests/test_integration.py
collective/contentgroups/tests/test_plugin.py
collective/contentgroups/tests/test_setup.py
collective/contentgroups/tests/test_utils.py
collective/contentgroups/tests/testing.zcml
collective/contentgroups/tests/profile/metadata.xml
collective/contentgroups/tests/profile/types.xml
collective/contentgroups/tests/profile/types/Container.xml
collective/contentgroups/tests/profile/types/Group.xml
collective.contentgroups-1.0.0a1.dist-info/LICENSE.GPL
collective.contentgroups-1.0.0a1.dist-info/LICENSE.rst
collective.contentgroups-1.0.0a1.dist-info/METADATA
collective.contentgroups-1.0.0a1.dist-info/WHEEL
collective.contentgroups-1.0.0a1.dist-info/entry_points.txt
collective.contentgroups-1.0.0a1.dist-info/namespace_packages.txt
collective.contentgroups-1.0.0a1.dist-info/top_level.txt
collective.contentgroups-1.0.0a1.dist-info/RECORD
