Metadata-Version: 2.1
Name: collective.contentgroups
Version: 1.0.0a1
Summary: Plone PAS plugin for content as groups
Home-page: https://github.com/collective/collective.contentgroups
Author: Maurits van Rees
Author-email: m.van.rees@zestsoftware.nl
License: GPL version 2
Keywords: Python Plone
Platform: UNKNOWN
Classifier: Development Status :: 3 - Alpha
Classifier: Environment :: Web Environment
Classifier: Framework :: Plone
Classifier: Framework :: Plone :: 5.2
Classifier: Programming Language :: Python
Classifier: Programming Language :: Python :: 2.7
Classifier: Programming Language :: Python :: 3.6
Classifier: Operating System :: OS Independent
Classifier: License :: OSI Approved :: GNU General Public License v2 (GPLv2)
Requires-Dist: Products.GenericSetup (>=1.8.2)
Requires-Dist: plone.api
Requires-Dist: setuptools
Requires-Dist: six
Provides-Extra: test
Requires-Dist: plone.app.testing ; extra == 'test'
Requires-Dist: plone.testing (>=5.0.0) ; extra == 'test'
